examon_pcep_package/__init__.py
examon_pcep_package/questions.py
examon_pcep_package-0.5.1.dist-info/METADATA
examon_pcep_package-0.5.1.dist-info/WHEEL
examon_pcep_package-0.5.1.dist-info/RECORD
