Metadata-Version: 2.1
Name: examon_pcep_package
Version: 0.5.1
Summary: 
Author: Jarrod Folino
Author-email: jdfolino@icloud.com
Requires-Python: >=3.11,<3.12
Classifier: Programming Language :: Python :: 3
Classifier: Programming Language :: Python :: 3.11
Requires-Dist: examon-core (==2.0.5)
